MANIFEST.in
README.md
UNLICENSE
readme.md
setup.py
tests/functional_runner.py
tests/helpers.py
tests/test_absolute_number_ambiguity.py
tests/test_anime_filenames.py
tests/test_configfunctional.py
tests/test_custom_replacement.py
tests/test_datestamp_episode.py
tests/test_extension_pattern.py
tests/test_filename_blacklist.py
tests/test_fileparse_api.py
tests/test_files.py
tests/test_force_series.py
tests/test_functional.py
tests/test_invalid_files.py
tests/test_limit_by_extension.py
tests/test_movingfiles.py
tests/test_multiepisode_filenames.py
tests/test_name_generation.py
tests/test_no_series_in_filename.py
tests/test_override_seriesname.py
tests/test_parsing.py
tests/test_safefilename.py
tests/test_series_replacement.py
tests/test_system.py
tvnamer/__init__.py
tvnamer/__main__.py
tvnamer/_titlecase.py
tvnamer/cliarg_parser.py
tvnamer/compat.py
tvnamer/config.py
tvnamer/config_defaults.py
tvnamer/main.py
tvnamer/tvnamer_exceptions.py
tvnamer/unicode_helper.py
tvnamer/utils.py
tvnamer.egg-info/PKG-INFO
tvnamer.egg-info/SOURCES.txt
tvnamer.egg-info/dependency_links.txt
tvnamer.egg-info/entry_points.txt
tvnamer.egg-info/requires.txt
tvnamer.egg-info/top_level.txt